{"_id":{"$oid":"5c8d67ec04f79c4c47584284"},"competition":"5c8d5a2ed8ce053e949543db","name":"Edsbergsskolan","scores":[0,0,0,0,0,0,0,0],"answers":[[],[],[],[],[],[],[],[]]}
{"_id":{"$oid":"5c8d67f204f79c4c47584285"},"competition":"5c8d5a2ed8ce053e949543db","name":"Berzeliusskolan","scores":[0,0,0,0,0,0,0,0],"answers":[[],[],[],[],[],[],[],[]]}
{"_id":{"$oid":"5c8d687b04f79c4c47584286"},"competition":"5c8d5a2ed8ce053e949543db","name":"Österslättskolan","scores":[0,0,0,0,0,0,0,0],"answers":[[],[],[],[],[],[],[],[]]}
{"_id":{"$oid":"5c9cb8ec2a4ab45492e8475a"},"competition":"5c8d5a2ed8ce053e949543db","name":"Ett fjärde lag","scores":[0,0,0,0,0,0,0,0],"answers":[[],[],[],[],[],[],[],[]]}
{"_id":{"$oid":"5c9e0deb1ed48348329d819e"},"competition":"5c9ddcef956edd1d96a61f38","name":"Tunaskolan","scores":[0,0,0,0,0,0,8,0],"answers":[[],[],[],[],[],[],["hdjshskjfhs"],[]]}
{"_id":{"$oid":"5c9e0df81ed48348329d819f"},"competition":"5c9ddcef956edd1d96a61f38","name":"Nosabyskolan","scores":[0,0,0,2,0,0,2,0],"answers":[[],["Frukt","Korv"],[],[],[],[],[],[]]}
{"_id":{"$oid":"5ca5b9bd1b107e4e097a89d8"},"competition":"5ca4b27a360fc24c9b81ecf5","name":"Ekholmsskolan 8A","scores":[4,1,1,4,9,6,1,10],"answers":[[],[],["Häst","Budbärare","Fyrtorn","Meteor","Komet"],[false,false,true,false,true,true],[],["Gå\nHöger\nGå\nVänster \nGå\nGå\nHöger\nGå\nVänster\nGå\nGå\nHöger \nGå"],[],[]]}
{"_id":{"$oid":"5ca5c0701b107e4e097a89d9"},"competition":"5ca4b27a360fc24c9b81ecf5","name":"Berzeliusskolan 8S","scores":[3,3,4,4,10,6,3,10],"answers":[[],["620","70"],["Komet","Stjärna","Komet","Komet","Komet"],[false,false,true,false,true,true],[],["Gå\nHöger\nGå\nVänster\nGå\nGå\nHöger\nGå\nVänster\nGå\nGå\nHöger\nGå"],[],[]]}
{"_id":{"$oid":"5ca5c39f1b107e4e097a89da"},"competition":"5ca4ad7203fd813219ceed06","name":"Team 8 Erlaskolan","scores":[4,4,6,5,1,6,0,0],"answers":[[],[],[],[],[],[],["2,160 sekunder","71680 s"],["Hjule",null,null,"Kil","Hävstång"]]}
{"_id":{"$oid":"5ca7256c1b107e4e097a8cfd"},"competition":"5ca723171b107e4e097a8c99","name":"8A Int. Engelska skolan","scores":[4,2,4,4,10,6,1,9],"answers":[[],["26800"],["Satellit","Komet","Komet","Komet","Komet"],[],[],["Gå \nHöger\nGå\nVänster\nGå\nGå\nHöger\nGå\nVänster\nGå\nGå\nHöger\nGå"],[],[]]}
{"_id":{"$oid":"5ca725b91b107e4e097a8cfe"},"competition":"5ca723171b107e4e097a8c99","name":"8C Rättviksskolan","scores":[3,1,0,5,10,6,2,3],"answers":[[],["1393080"],["Rockstjärno","Kyrkan klocka","Kyrka","Metiroit","Metiorit"],[],[],["Gå höger gå vänster gå gå höger gå vänster gå gå höger gå"],[],[]]}
{"_id":{"$oid":"5ca725ce1b107e4e097a8cff"},"competition":"5ca723171b107e4e097a8c99","name":"8D Petreskolan","scores":[4,3,3,4,10,6,1,4],"answers":[[],["13399.9","171866.5"],["Satelit","Solen","Komet","Komet","Komet"],[],[],["Gå\nHöger\nGå\nVänster\nGå\nGå\nHöger\nGå\nVänster \nGå \nGå\nHöger \nGå"],[],[]]}
{"_id":{"$oid":"5ca725e21b107e4e097a8d00"},"competition":"5ca725281b107e4e097a8ccc","name":"Team 8 Erlaskolan","scores":[2,3,2,3,10,6,1,7],"answers":[[],["23226","30"],["Satellit","Budbärare",null,"Komet","Komet"],[],[],["Gå\nHöger\nGå\nVänster\nGå\nGå\nHöger\nGå\nVänster\nGå\nGå\nHöger\nGå"],[],[]]}
{"_id":{"$oid":"5ca725ed1b107e4e097a8d01"},"competition":"5ca725281b107e4e097a8ccc","name":"8EF Rotskärsskolan","scores":[4,2,1,3,2,6,0,5],"answers":[[],["9782000","13042666"],[null,"Vinden","Berg","Meteor","Komet"],[],[],["Gå \nHöger \nGå\nVänster \nGå \nGå \nHöger \nGå \nVänster \nGå \nGå \nHöger \nGå"],[],[]]}
{"_id":{"$oid":"5ca725f81b107e4e097a8d02"},"competition":"5ca725281b107e4e097a8ccc","name":"8F Maserskolan","scores":[3,2,0,5,9,6,3,3],"answers":[[],[],["Satellit","Satellit","Asteroid","Asteroid","Asteroid"],[],[],["Gå \nHöger \nGå \nVänster \nGå \nGå\nHöger \nGå\nVänster \nGå\nGå \nHöger \nGå"],[],[]]}
{"_id":{"$oid":"5ca79cb11b107e4e097a8d7b"},"competition":"5ca4ad7203fd813219ceed06","name":"8A Int. Engelska Skolan","scores":[6,4,5,5,0,5,6,3],"answers":[[],[],[],[],[],[],["21 600 sekunder","560 sekunder"],["Klocka","Klocka","Skruv","Skruv","Skruv"]]}
{"_id":{"$oid":"5ca79cba1b107e4e097a8d7c"},"competition":"5ca4ad7203fd813219ceed06","name":"8D Petreskolan","scores":[4,4,6,5,0,5,0,3],"answers":[[],[],[],[],[],[],["54000000000 h","70"],["Hjul","Ramp","Skruvar","Skruvar","Skruvar"]]}
{"_id":{"$oid":"5cac7adc1b107e4e097a9116"},"competition":"5ca4b27a360fc24c9b81ecf5","name":"Ekholmsskolan 8B","scores":[2,2,1,5,10,6,1,4],"answers":[[],[],[],[],[],[],[],[]]}
{"_id":{"$oid":"5cad923e1b107e4e097a9177"},"competition":"5cad8ed41b107e4e097a9149","name":"Kristofferskolan 8b2","scores":[0,0,0,0,0,0,0],"answers":[[],[],[],[],[],[],[]]}
{"_id":{"$oid":"5cad92401b107e4e097a9178"},"competition":"5cad8ed41b107e4e097a9149","name":"Täby Friskola","scores":[0,0,0,0,0,0,0],"answers":[[],[],[],[],[],[],[]]}
{"_id":{"$oid":"5cad924d1b107e4e097a9179"},"competition":"5cad8ed41b107e4e097a9149","name":"Södertörns friskola 8Nv2","scores":[0,0,0,0,0,0,0],"answers":[[],[],[],[],[],[],[]]}
{"_id":{"$oid":"5cadada71b107e4e097a9212"},"competition":"5cad8ed31b107e4e097a9118","name":"Lag A","scores":[0,4,2,0,0,0,0,0],"answers":[[],[],[],["\u003cimg src=\"uploads/landskapsforandringar.jpg\"\u003e;\u003cimg src=\"uploads/skordar.jpg\"\u003e"],[],[],[],[]]}
{"_id":{"$oid":"5cadadb11b107e4e097a9213"},"competition":"5cad8ed31b107e4e097a9118","name":"Lag B","scores":[2,6,4,0,0,0,3,0],"answers":[[],[],[],[],[],[],[],[]]}
{"_id":{"$oid":"5cadadb31b107e4e097a9214"},"competition":"5cad8ed31b107e4e097a9118","name":"Lag C","scores":[0,4,4,0,0,3,null,3],"answers":[[],[],[true,true,null,true,true,false],["\u003cimg src=\"uploads/ebola.jpg\"\u003e;\u003cimg src=\"uploads/kartor.jpg\"\u003e;\u003cimg src=\"uploads/landskapsforandringar.jpg\"\u003e;\u003cimg src=\"uploads/luftkvalitet.jpg\"\u003e;\u003cimg src=\"uploads/naturkatastrofer.jpg\"\u003e;\u003cimg src=\"uploads/vader.jpg\"\u003e"],[],[],["9","Y"],["F","Skruv","Hål","Skruven","Skruv"]]}
{"_id":{"$oid":"5cadf7961b107e4e097a936c"},"competition":"5cadf6df1b107e4e097a933b","name":"Ellen Keyskolan 8K","scores":[3,2,0,5,0,6,0,1],"answers":[[],["26799,9"],["Båt","Död","Meteor","Bergskedjor","Norrsken"],[false,false,false,false,true,true],[],["Gå\nHöger\nGå\nVänster\nGå \nGå\nHöger\nGå \nVänster\nGå\nGå\nHöger\nGå"],[],[]]}
{"_id":{"$oid":"5cadf79a1b107e4e097a936d"},"competition":"5cadf6df1b107e4e097a933b","name":"Mosstorpsskolan 8A","scores":[4,3,2,5,7,6,1,9],"answers":[[],["2679","3573"],["Sattelit","Bild","Sateli","Komet","Komet"],[false,false,false,false,true,true],[],["Gå\nHöger\nGå\nVänster\nGå\nGå\nHöger\nGå\nVänster\nGå\nGå\nHöger\nGå"],[],[]]}
{"_id":{"$oid":"5cadf79b1b107e4e097a936e"},"competition":"5cadf6df1b107e4e097a933b","name":"Ydreskolan 8B","scores":[3,2,2,4,10,6,1,4],"answers":[[],[],["Satelit","Sosi","Asteriod","Komet","Komet"],[false,false,true,false,true,true],[],["Gå\nHöger\nGå\nVänster\nGå\nGå\nHöger\nGå\nVänster\nGå\nGå\nHöger\nGå"],[],[]]}
{"_id":{"$oid":"5cae46198fff7803823ec923"},"competition":"5cae45d28fff7803823ec896","name":"Kristofferskolan 8b2","scores":[15,2,3,3,7,6,3],"answers":[[],["2445500","3260666667"],["Satellit","Stjärnor","Komet","Komet","Komet"],[false,false,true,false,null,true],[],["Gå höger gå vänster gå gå höger gå vänster gå gå höger gå"],[]]}
{"_id":{"$oid":"5cae461b8fff7803823ec924"},"competition":"5cae45d28fff7803823ec896","name":"Södertörns friskola 8Nv2","scores":[18,3,2,5,10,6,2],"answers":[[],["6700 gram","17866 st"],["Satellit","Satellit","Satellit","Kommet","Komet"],[false,false,false,false,true,true],[],["Gå\nHöger\nGå\nVänster\nGå\nGå\nHöger\nGå\nVänster\nGå\nGå\nHöger\nGå"],[]]}
{"_id":{"$oid":"5cae46238fff7803823ec925"},"competition":"5cae45d28fff7803823ec896","name":"Skolhagenskolan 8b","scores":[18,6,5,5,10,6,0],"answers":[[],["348400","929"],["Komet","Komet","Komet","Komet","Komet"],[false,false,false,false,true,false],[],["Gå\nHöger\nGå\nVänster\nGå\nGå\nHöger\nGå\nVänster\nGå\nGå\nHöger\nGå"],[]]}
{"_id":{"$oid":"5cae46318fff7803823ec926"},"competition":"5cae45d48fff7803823ec8c4","name":"Täby Friskola","scores":[8,4,2,4,10,6,0],"answers":[[],["6700","9"],["Satellit","Månen","Asteroid","Komet","Komet"],[false,false,true,false,true,true],[],["Gå\nHöger\nGå\nVänster\nGå\nGå\nHöger\nGå\nVänster\nGå\nGå\nHöger\nGå"],[]]}
{"_id":{"$oid":"5cae46398fff7803823ec927"},"competition":"5cae45d48fff7803823ec8c4","name":"Mälarhöjdens skola 8NO3","scores":[7,3,5,6,8,6,1],"answers":[[],["8040","21440"],["Komet","Komet","Komet","Komet","Komet"],[true,false,false,false,true,true],[],["Gå\nHöger \nGå\nVänster\nGå\nGå\nHöger\nGå\nVänster\nGå\nGå\nHöger\nGå"],[]]}
{"_id":{"$oid":"5cae46408fff7803823ec928"},"competition":"5cae45d48fff7803823ec8c4","name":"Näsbydalskolan 8M","scores":[12,3,2,3,9,6,1],"answers":[[],["6700","12"],["Satellit","Satellit","Asteroid","Komet","Komet"],[false,true,true,false,true,true],[],["Gå\nHöger\nGå\nVänster\nGå\nGå\nHöger\nGå\nVänster\nGå\nGå\nHöger\nGå"],[]]}
{"_id":{"$oid":"5caeef8e8fff7803823ec92b"},"competition":"5caddfdb1b107e4e097a9289","name":"Nosabyskolan","scores":[2,1,2,4,9,6,2,1],"answers":[[],[],["Teleskop","Budbärare","Pla","Kometer","Komet"],[false,false,true,false,true,true],[],[],[],[]]}
{"_id":{"$oid":"5caeefa68fff7803823ec92c"},"competition":"5caddfdb1b107e4e097a9289","name":"Barsebäck Montessori","scores":[1,2,0,4,10,4,3,3],"answers":[[],[],["Satellit",null,"Asteroid","Asteroid","Asteroid"],[false,false,null,false,true,true],[],["Gå\nGå\nGå\nHöger\nGå\nGå\nVänster\nGå\nGå\nHöger\nGå"],[],[]]}
{"_id":{"$oid":"5caf02e38fff7803823ec92d"},"competition":"5cae088e1b107e4e097a9445","name":"Tunaskolan","scores":[1,1,1,3,10,6,0,14],"answers":[[],["118500","158000"],["Satelliter","Post",null,"Asteriod","Komet"],[false,true,false,false,false,true],[],["Gå, höger, gå, vänster, gå, gå, höger, gå, vänster, gå, gå, höger, gå"],[],[]]}
{"_id":{"$oid":"5caf02eb8fff7803823ec92e"},"competition":"5cae088e1b107e4e097a9445","name":"Kunskapsskolan","scores":[1,1,0,5,8,6,1,6],"answers":[[],[null,"100"],["Mobilabonnemang","Budbärare","Postkontor","Glaciär","Meteor"],[false,false,false,false,true,true],[],["Gå\nHöger\nGå\nVänster \nGå\nGå\nHöger\nGå\nVänster\nGå\nGå\nHöger\nGå"],[],[]]}
{"_id":{"$oid":"5caf10848fff7803823ec92f"},"competition":"5ca4ad6f03fd813219ceecd5","name":"Tunaskolan","scores":[4,4,5,4,0,6,3,3],"answers":[[],[],[true,false,false,false,true,false],[],[],[],[],["Arkimedes skruv","Skruv","Ark","Skruv","Skruv"]]}
{"_id":{"$oid":"5caf108e8fff7803823ec930"},"competition":"5ca4ad6f03fd813219ceecd5","name":"Barsebäck Montessori","scores":[4,4,5,5,3,2,0,0],"answers":[[],[],[true,false,false,false,true,false],["\u003cimg src=\"uploads/kartor.jpg\"\u003e;\u003cimg src=\"uploads/landskapsforandringar.jpg\"\u003e;\u003cimg src=\"uploads/naturkatastrofer.jpg\"\u003e;\u003cimg src=\"uploads/skordar.jpg\"\u003e;\u003cimg src=\"uploads/trafikledning.jpg\"\u003e;\u003cimg src=\"uploads/vader.jpg\"\u003e"],[],[],[],[null,"Hävstång","Dammsugare","Hävstång","Hävstång"]]}
{"_id":{"$oid":"5caf1b228fff7803823ec931"},"competition":"5cae21c21b107e4e097a9564","name":"Ekholmsskolan 8A","scores":[6,4,5,4,6,4,3,0],"answers":[[],[],[true,null,false,false,true,false],["\u003cimg src=\"uploads/kartor.jpg\"\u003e;\u003cimg src=\"uploads/landskapsforandringar.jpg\"\u003e;\u003cimg src=\"uploads/mobiltelefoner.jpg\"\u003e;\u003cimg src=\"uploads/naturkatastrofer.jpg\"\u003e;\u003cimg src=\"uploads/trafikledning.jpg\"\u003e;\u003cimg src=\"uploads/vader.jpg\"\u003e"],[],[],["560 sek","70 sek"],["Vågen","T","Påle","Elektromagnet","Hävstång"]]}
{"_id":{"$oid":"5caf1b3e8fff7803823ec932"},"competition":"5cae21c21b107e4e097a9564","name":"Mosstorpsskolan 8A","scores":[4,3,4,3,3,6,0,1],"answers":[[],[],[true,true,false,true,false,false],["\u003cimg src=\"uploads/internettrafik.jpg\"\u003e;\u003cimg src=\"uploads/kartor.jpg\"\u003e;\u003cimg src=\"uploads/landskapsforandringar.jpg\"\u003e;\u003cimg src=\"uploads/mobiltelefoner.jpg\"\u003e;\u003cimg src=\"uploads/trafikledning.jpg\"\u003e;\u003cimg src=\"uploads/vader.jpg\"\u003e"],[],[],["12"],["Solur","Pendelur","Dato","Hävstång","Skruv"]]}
{"_id":{"$oid":"5caf1b3f8fff7803823ec933"},"competition":"5cae21c21b107e4e097a9564","name":"Berzeliusskolan 8S","scores":[6,4,6,5,0,5,3,3],"answers":[[],[],[true,true,false,false,true,false],["\u003cimg src=\"uploads/ebola.jpg\"\u003e;\u003cimg src=\"uploads/kartor.jpg\"\u003e;\u003cimg src=\"uploads/landskapsforandringar.jpg\"\u003e;\u003cimg src=\"uploads/mobiltelefoner.jpg\"\u003e;\u003cimg src=\"uploads/naturkatastrofer.jpg\"\u003e;\u003cimg src=\"uploads/vader.jpg\"\u003e"],[],[],["216000000 s","560 s"],["Hävstång","Hävstång","Skruv","Skruv","Skruv"]]}
{"_id":{"$oid":"5caf24308fff7803823ec934"},"competition":"5cae45f58fff7803823ec8f2","name":"Skolhagenskolan 8b","scores":[6,4,5,4,6,4,6,0],"answers":[[],[],[true,false,false,false,true,false],["\u003cimg src=\"uploads/kartor.jpg\"\u003e;\u003cimg src=\"uploads/landskapsforandringar.jpg\"\u003e;\u003cimg src=\"uploads/mobiltelefoner.jpg\"\u003e;\u003cimg src=\"uploads/naturkatastrofer.jpg\"\u003e;\u003cimg src=\"uploads/trafikledning.jpg\"\u003e;\u003cimg src=\"uploads/vader.jpg\"\u003e"],[],[],["21600 s","560 s"],["Våg","Båt","Skruvmejsel","Hjul","Spik"]]}
{"_id":{"$oid":"5caf24328fff7803823ec935"},"competition":"5cae45f58fff7803823ec8f2","name":"Näsbydalskolan 8M","scores":[6,4,5,4,3,6,3,3],"answers":[[],[],[true,false,false,false,true,false],["\u003cimg src=\"uploads/kartor.jpg\"\u003e;\u003cimg src=\"uploads/landskapsforandringar.jpg\"\u003e;\u003cimg src=\"uploads/mobiltelefoner.jpg\"\u003e;\u003cimg src=\"uploads/naturkatastrofer.jpg\"\u003e;\u003cimg src=\"uploads/trafikledning.jpg\"\u003e;\u003cimg src=\"uploads/vader.jpg\"\u003e"],[],[],["21600","5231584821"],["Hjulet","Hjulet","Skruv","Skruv","Skruv"]]}
{"_id":{"$oid":"5caf24678fff7803823ec936"},"competition":"5cae45f58fff7803823ec8f2","name":"Södertörns friskola 8Nv2","scores":[6,4,6,5,1,4,3,0],"answers":[[],[],[true,true,false,false,true,false],["\u003cimg src=\"uploads/internettrafik.jpg\"\u003e;\u003cimg src=\"uploads/kartor.jpg\"\u003e;\u003cimg src=\"uploads/landskapsforandringar.jpg\"\u003e;\u003cimg src=\"uploads/naturkatastrofer.jpg\"\u003e;\u003cimg src=\"uploads/skordar.jpg\"\u003e;\u003cimg src=\"uploads/vader.jpg\"\u003e"],[],[],["21600","22160"],["Våg","Våg","Våg","Våg","Hävstång"]]}
{"_id":{"$oid":"5cb5cf62ab8f6f0db19d29e7"},"competition":"5cb5caa3ab8f6f0db19d29b6","name":"Malmö","scores":[3,0,0,0,0,0,0,0],"answers":[[],[],[],[],[],[],[],[]]}
{"_id":{"$oid":"5cb5cf6bab8f6f0db19d29e8"},"competition":"5cb5caa3ab8f6f0db19d29b6","name":"Lund","scores":[2,0,0,0,0,0,0,0],"answers":[[],[],[],[],[],[],[],[]]}
{"_id":{"$oid":"5cb5cf6fab8f6f0db19d29e9"},"competition":"5cb5caa3ab8f6f0db19d29b6","name":"Kristianstad","scores":[0,0,0,0,0,0,0,0],"answers":[[],[],[],[],[],[],[],[]]}
{"_id":{"$oid":"5cb5cf78ab8f6f0db19d29ea"},"competition":"5cb5caa3ab8f6f0db19d29b6","name":"Stockholm","scores":[2,0,0,0,0,0,0,0],"answers":[[],[],[],[],[],[],[],[]]}
{"_id":{"$oid":"5cc2f1ebf9e387304a1a5bdb"},"competition":"5cc198fff9e387304a1a50cf","name":"Lag 1","scores":[0,0,0,0,0,0,0,0],"answers":[[],[],[],[],[],[],[],[]]}
{"_id":{"$oid":"5ce56ccabadf2733362dc9a1"},"competition":"5cc198fff9e387304a1a50cf","name":"Lag 2","scores":[0,0,0,0,0,0,0,0],"answers":[[],[],[],[],[],[],[true],[]]}
{"_id":{"$oid":"5ce56ccebadf2733362dc9a2"},"competition":"5cc198fff9e387304a1a50cf","name":"ASDdgsda","scores":[0,0,0,0,0,0,0,0],"answers":[[],[],[],[],[],[],[false],[]]}
{"_id":{"$oid":"5ce56cd1badf2733362dc9a3"},"competition":"5cc198fff9e387304a1a50cf","name":"Hejsan hoppsan","scores":[0,0,0,0,0,0,0,0],"answers":[[],[],[],[],[],[],[],[]]}
{"_id":{"$oid":"5ce66d05badf2733362dcac0"},"competition":"5cc6adbcb75bc855f981cd1d","name":"Ekholmsskolan","scores":[8,2,3,3,2,7,5,0],"answers":[[],["Natriumdivätefosfat","","Askorbinsyra","Natriumklorid"],["Mac id","Mac id","Månlandning","Månlandning","Månlandning"],["b)\u0009Månen saknar atmosfär och flaggan skulle därför hänga rakt ner utan pinnen.","c)\u0009Hammaren landar på marken efter ungefär 30 sekunder och fjädern efter några minuter.","Falskt","Sant","Sant"],["S","Z","M"],["D","D","C","A","B","C","D","D","D","A","A","B","B","C","A","D","D","C","B","A"],[true,false,true,false,false,false],[]]}
{"_id":{"$oid":"5ce66d06badf2733362dcac1"},"competition":"5cc6adbcb75bc855f981cd1d","name":"Friskolan Svettpärlan","scores":[5,6,5,4,2,5,4,4],"answers":[[],[],["Månlanding","Månlandningen","Månlandningen","Månlandningen","Månlandningen"],["b)\u0009Månen saknar atmosfär och flaggan skulle därför hänga rakt ner utan pinnen.","d)\u0009Hammaren och fjädern landar exakt samtidigt på månytan.","Sant","Sant","Falskt"],["A","T","K"],["D","C","C","A","D","D","B","D","B","B","A","B","B","C","C","C","D","C","B","A"],[true,false,false,false,false,false],[]]}
{"_id":{"$oid":"5ce66d07badf2733362dcac2"},"competition":"5cc6adbcb75bc855f981cd1d","name":"Tunaskolan","scores":[8,0,3,5,0,6,6,0],"answers":[[],["Askorbinsya","Ssaackar"],["911","Svarthål bild","Månlandningen","Månlandningen","Månlandningen"],["b)\u0009Månen saknar atmosfär och flaggan skulle därför hänga rakt ner utan pinnen.","d)\u0009Hammaren och fjädern landar exakt samtidigt på månytan.","Falskt","Sant","Falskt"],["H","E","J"],["D","D","C","A","C","C","B","D","C","B","A","B","A","C","B","D","D","C","B","C"],[false,false,true,false,false,false],[]]}
{"_id":{"$oid":"5ce66d08badf2733362dcac3"},"competition":"5cc6adbcb75bc855f981cd1d","name":"Vasaskolan","scores":[5,0,5,4,0,6,5,0],"answers":[[],[],["Månlandningen","Månlandningen","Månlandningen","Månlandningen","Månlandningen"],["b)\u0009Månen saknar atmosfär och flaggan skulle därför hänga rakt ner utan pinnen.","d)\u0009Hammaren och fjädern landar exakt samtidigt på månytan.","Sant","Sant","Falskt"],["H","M","A"],["D","C","C","A","C","C","B","D","C","B","A","B","B","A","C","D","D","A","B","A"],[false,false,true,false,true,false],[]]}
